["{\n    \"duree_suivi_y\": 7,\n    \"surface_CR_totale\": 195.9348,\n    \"surface_foret_ha\": 1846.9382,\n    \"surface_foret_ha_feuillus\": 1193.8443,\n    \"surface_foret_ha_coniferes\": 282.5774,\n    \"surface_foret_ha_autres\": 370.5164,\n    \"surface_CR_feuillus\": 134.1249,\n    \"surface_CR_coniferes\": 39.0775,\n    \"surface_CR_autres\": 22.7324,\n    \"pourcentage_CR_foret_total\": 10.6086,\n    \"pourcentage_CR_foret_total_feuillus\": 11.2347,\n    \"pourcentage_CR_foret_total_coniferes\": 13.8289,\n    \"pourcentage_CR_foret_total_autres\": 6.1353,\n    \"pourcentage_CR_foret_par_an\": 1.5155,\n    \"pourcentage_CR_foret_par_an_feuillus\": 1.605,\n    \"pourcentage_CR_foret_par_an_coniferes\": 1.9756,\n    \"pourcentage_CR_foret_par_an_autres\": 0.8765,\n    \"ha_par_an\": 27.9907,\n    \"temps_cycle\": 65.984,\n    \"temps_restant\": 58.984\n}\n"]
